odoo/addons/hr_operating_unit/README.rst
odoo/addons/hr_operating_unit/__init__.py
odoo/addons/hr_operating_unit/__manifest__.py
odoo/addons/hr_operating_unit/i18n/es.po
odoo/addons/hr_operating_unit/i18n/hr_operating_unit.pot
odoo/addons/hr_operating_unit/migrations/14.0.1.0.0/pre-migration.py
odoo/addons/hr_operating_unit/models/__init__.py
odoo/addons/hr_operating_unit/models/hr_employee_base.py
odoo/addons/hr_operating_unit/models/hr_operating_unit.py
odoo/addons/hr_operating_unit/readme/CONTRIBUTORS.rst
odoo/addons/hr_operating_unit/readme/DESCRIPTION.rst
odoo/addons/hr_operating_unit/readme/USAGE.rst
odoo/addons/hr_operating_unit/security/security.xml
odoo/addons/hr_operating_unit/static/description/icon.png
odoo/addons/hr_operating_unit/static/description/index.html
odoo/addons/hr_operating_unit/views/hr_employee.xml
odoo14_addon_hr_operating_unit-14.0.1.1.0.dist-info/METADATA
odoo14_addon_hr_operating_unit-14.0.1.1.0.dist-info/WHEEL
odoo14_addon_hr_operating_unit-14.0.1.1.0.dist-info/top_level.txt
odoo14_addon_hr_operating_unit-14.0.1.1.0.dist-info/RECORD
